ljson/__init__.py
ljson/base/__init__.py
ljson/base/disk.py
ljson/base/generic.py
ljson/base/mem.py
ljson/convert/__init__.py
ljson/convert/csv.py
ljson/convert/sql.py
ljson/slapdash/__init__.py
ljson/slapdash/disk.py
ljson/slapdash/generic.py
ljson/slapdash/mem.py
ljson-0.5.4.dist-info/DESCRIPTION.rst
ljson-0.5.4.dist-info/METADATA
ljson-0.5.4.dist-info/RECORD
ljson-0.5.4.dist-info/WHEEL
ljson-0.5.4.dist-info/metadata.json
ljson-0.5.4.dist-info/top_level.txt
test/__init__.py
test/data.py
test/test_ljson_convert_csv.py
test/test_ljson_disk.py
test/test_ljson_mem.py
test/test_slapdash_disk.py
test/test_slapdash_mem.py
