Metadata-Version: 2.0
Name: ljson
Version: 0.5.4
Summary: A table dataformat based on json
Home-page: https://github.com/daknuett/ljson
Author: Daniel Knüttel
Author-email: daknuett@gmail.com
License: AGPL v3
Keywords: data storage table json
Platform: UNKNOWN
Classifier: Development Status :: 4 - Beta
Classifier: Intended Audience :: Developers
Classifier: License :: OSI Approved :: GNU Affero General Public License v3
Classifier: Programming Language :: Python :: 3
Provides-Extra: ljson.convert.sql
Requires-Dist: pymysql; extra == 'ljson.convert.sql'
